LICENSE
MANIFEST.in
README.md
requirements.txt
setup.cfg
setup.py
mblog/README.md
mblog/__init__.py
mblog/__main__.py
mblog/config.py
mblog/controller.py
mblog/models.py
mblog/routes.py
mblog/security.py
mblog/util.py
mblog.egg-info/PKG-INFO
mblog.egg-info/SOURCES.txt
mblog.egg-info/dependency_links.txt
mblog.egg-info/entry_points.txt
mblog.egg-info/not-zip-safe
mblog.egg-info/requires.txt
mblog.egg-info/top_level.txt
mblog/static/robots.txt
mblog/static/css/bootstrap-theme.css
mblog/static/css/bootstrap.css
mblog/static/css/config.json
mblog/static/css/custom.css
mblog/static/css/hilite.css
mblog/static/css/normalize.css
mblog/static/css/simplemde.css
mblog/static/fonts/glyphicons-halflings-regular.eot
mblog/static/fonts/glyphicons-halflings-regular.svg
mblog/static/fonts/glyphicons-halflings-regular.ttf
mblog/static/fonts/glyphicons-halflings-regular.woff
mblog/static/fonts/glyphicons-halflings-regular.woff2
mblog/static/images/favicon.ico
mblog/static/images/logo.png
mblog/static/js/bootstrap.js
mblog/static/js/jquery-1.11.0.min.js
mblog/static/js/simplemde.js
mblog/templates/base.html
mblog/templates/create.html
mblog/templates/delete.html
mblog/templates/detail.html
mblog/templates/edit.html
mblog/templates/error.html
mblog/templates/index.html
mblog/templates/login.html
mblog/templates/logout.html
mblog/templates/notfound.html
mblog/templates/upload.html
mblog/templates/includes/pagination.html